README.rst
setup.py
allenite_api/__init__.py
allenite_api/alleniteclient.py
allenite_api/exceptions.py
py_allenite.egg-info/PKG-INFO
py_allenite.egg-info/SOURCES.txt
py_allenite.egg-info/dependency_links.txt
py_allenite.egg-info/requires.txt
py_allenite.egg-info/top_level.txt
test/__init__.py
test/test_endpoints.py