Metadata-Version: 1.1
Name: py-allenite
Version: 0.2.0
Summary: Python wrapper for Allenite's API.
Home-page: https://github.com/lamergameryt/py-allenite
Author: Harsh Patil
Author-email: ifung230@gmail.com
License: UNKNOWN
Download-URL: https://github.com/lamergameryt/py-allenite
Keywords: python,allenite
Platform: UNKNOWN
Classifier: Intended Audience :: Developers
Classifier: License :: OSI Approved :: GNU General Public License v3 (GPLv3)
Classifier: Operating System :: OS Independent
Classifier: Programming Language :: Python
Classifier: Programming Language :: Python :: 3
Classifier: Programming Language :: Python :: 3.6
Classifier: Programming Language :: Python :: 3.7
Classifier: Programming Language :: Python :: 3.8
Classifier: Programming Language :: Python :: 3.9
